{"nodes": [{"id": "ephemeral", "label": "ephemeral.go", "file_type": "code", "source_file": ".graphify_scope/pkg/kt/command/exchange/ephemeral.go", "source_location": "L1"}, {"id": "ephemeral_byephemeralcontainer", "label": "ByEphemeralContainer()", "file_type": "code", "source_file": ".graphify_scope/pkg/kt/command/exchange/ephemeral.go", "source_location": "L18"}, {"id": "ephemeral_getpodsofresource", "label": "getPodsOfResource()", "file_type": "code", "source_file": ".graphify_scope/pkg/kt/command/exchange/ephemeral.go", "source_location": "L49"}, {"id": "ephemeral_getpodsofservice", "label": "getPodsOfService()", "file_type": "code", "source_file": ".graphify_scope/pkg/kt/command/exchange/ephemeral.go", "source_location": "L71"}, {"id": "ephemeral_createephemeralcontainer", "label": "createEphemeralContainer()", "file_type": "code", "source_file": ".graphify_scope/pkg/kt/command/exchange/ephemeral.go", "source_location": "L83"}, {"id": "ephemeral_isephemeralcontainerready", "label": "isEphemeralContainerReady()", "file_type": "code", "source_file": ".graphify_scope/pkg/kt/command/exchange/ephemeral.go", "source_location": "L105"}, {"id": "ephemeral_exchangewithephemeralcontainer", "label": "exchangeWithEphemeralContainer()", "file_type": "code", "source_file": ".graphify_scope/pkg/kt/command/exchange/ephemeral.go", "source_location": "L124"}, {"id": "ephemeral_setupiptables", "label": "setupIptables()", "file_type": "code", "source_file": ".graphify_scope/pkg/kt/command/exchange/ephemeral.go", "source_location": "L153"}, {"id": "ephemeral_getlistenedports", "label": "getListenedPorts()", "file_type": "code", "source_file": ".graphify_scope/pkg/kt/command/exchange/ephemeral.go", "source_location": "L167"}, {"id": "ephemeral_remoteredirectport", "label": "remoteRedirectPort()", "file_type": "code", "source_file": ".graphify_scope/pkg/kt/command/exchange/ephemeral.go", "source_location": "L197"}, {"id": "ephemeral_randport", "label": "randPort()", "file_type": "code", "source_file": ".graphify_scope/pkg/kt/command/exchange/ephemeral.go", "source_location": "L215"}], "edges": [{"source": "ephemeral", "target": "fmt", "relation": "imports_from", "confidence": "EXTRACTED", "source_file": ".graphify_scope/pkg/kt/command/exchange/ephemeral.go", "source_location": "L4", "weight": 1.0}, {"source": "ephemeral", "target": "general", "relation": "imports_from", "confidence": "EXTRACTED", "source_file": ".graphify_scope/pkg/kt/command/exchange/ephemeral.go", "source_location": "L5", "weight": 1.0}, {"source": "ephemeral", "target": "options", "relation": "imports_from", "confidence": "EXTRACTED", "source_file": ".graphify_scope/pkg/kt/command/exchange/ephemeral.go", "source_location": "L6", "weight": 1.0}, {"source": "ephemeral", "target": "cluster", "relation": "imports_from", "confidence": "EXTRACTED", "source_file": ".graphify_scope/pkg/kt/command/exchange/ephemeral.go", "source_location": "L7", "weight": 1.0}, {"source": "ephemeral", "target": "sshchannel", "relation": "imports_from", "confidence": "EXTRACTED", "source_file": ".graphify_scope/pkg/kt/command/exchange/ephemeral.go", "source_location": "L8", "weight": 1.0}, {"source": "ephemeral", "target": "transmission", "relation": "imports_from", "confidence": "EXTRACTED", "source_file": ".graphify_scope/pkg/kt/command/exchange/ephemeral.go", "source_location": "L9", "weight": 1.0}, {"source": "ephemeral", "target": "util", "relation": "imports_from", "confidence": "EXTRACTED", "source_file": ".graphify_scope/pkg/kt/command/exchange/ephemeral.go", "source_location": "L10", "weight": 1.0}, {"source": "ephemeral", "target": "log", "relation": "imports_from", "confidence": "EXTRACTED", "source_file": ".graphify_scope/pkg/kt/command/exchange/ephemeral.go", "source_location": "L11", "weight": 1.0}, {"source": "ephemeral", "target": "v1", "relation": "imports_from", "confidence": "EXTRACTED", "source_file": ".graphify_scope/pkg/kt/command/exchange/ephemeral.go", "source_location": "L12", "weight": 1.0}, {"source": "ephemeral", "target": "strconv", "relation": "imports_from", "confidence": "EXTRACTED", "source_file": ".graphify_scope/pkg/kt/command/exchange/ephemeral.go", "source_location": "L13", "weight": 1.0}, {"source": "ephemeral", "target": "strings", "relation": "imports_from", "confidence": "EXTRACTED", "source_file": ".graphify_scope/pkg/kt/command/exchange/ephemeral.go", "source_location": "L14", "weight": 1.0}, {"source": "ephemeral", "target": "time", "relation": "imports_from", "confidence": "EXTRACTED", "source_file": ".graphify_scope/pkg/kt/command/exchange/ephemeral.go", "source_location": "L15", "weight": 1.0}, {"source": "ephemeral", "target": "ephemeral_byephemeralcontainer", "relation": "contains", "confidence": "EXTRACTED", "source_file": ".graphify_scope/pkg/kt/command/exchange/ephemeral.go", "source_location": "L18", "weight": 1.0}, {"source": "ephemeral", "target": "ephemeral_getpodsofresource", "relation": "contains", "confidence": "EXTRACTED", "source_file": ".graphify_scope/pkg/kt/command/exchange/ephemeral.go", "source_location": "L49", "weight": 1.0}, {"source": "ephemeral", "target": "ephemeral_getpodsofservice", "relation": "contains", "confidence": "EXTRACTED", "source_file": ".graphify_scope/pkg/kt/command/exchange/ephemeral.go", "source_location": "L71", "weight": 1.0}, {"source": "ephemeral", "target": "ephemeral_createephemeralcontainer", "relation": "contains", "confidence": "EXTRACTED", "source_file": ".graphify_scope/pkg/kt/command/exchange/ephemeral.go", "source_location": "L83", "weight": 1.0}, {"source": "ephemeral", "target": "ephemeral_isephemeralcontainerready", "relation": "contains", "confidence": "EXTRACTED", "source_file": ".graphify_scope/pkg/kt/command/exchange/ephemeral.go", "source_location": "L105", "weight": 1.0}, {"source": "ephemeral", "target": "ephemeral_exchangewithephemeralcontainer", "relation": "contains", "confidence": "EXTRACTED", "source_file": ".graphify_scope/pkg/kt/command/exchange/ephemeral.go", "source_location": "L124", "weight": 1.0}, {"source": "ephemeral", "target": "ephemeral_setupiptables", "relation": "contains", "confidence": "EXTRACTED", "source_file": ".graphify_scope/pkg/kt/command/exchange/ephemeral.go", "source_location": "L153", "weight": 1.0}, {"source": "ephemeral", "target": "ephemeral_getlistenedports", "relation": "contains", "confidence": "EXTRACTED", "source_file": ".graphify_scope/pkg/kt/command/exchange/ephemeral.go", "source_location": "L167", "weight": 1.0}, {"source": "ephemeral", "target": "ephemeral_remoteredirectport", "relation": "contains", "confidence": "EXTRACTED", "source_file": ".graphify_scope/pkg/kt/command/exchange/ephemeral.go", "source_location": "L197", "weight": 1.0}, {"source": "ephemeral", "target": "ephemeral_randport", "relation": "contains", "confidence": "EXTRACTED", "source_file": ".graphify_scope/pkg/kt/command/exchange/ephemeral.go", "source_location": "L215", "weight": 1.0}, {"source": "ephemeral_byephemeralcontainer", "target": "ephemeral_getpodsofresource", "relation": "calls", "confidence": "INFERRED", "source_file": ".graphify_scope/pkg/kt/command/exchange/ephemeral.go", "source_location": "L21", "weight": 0.8}, {"source": "ephemeral_byephemeralcontainer", "target": "ephemeral_createephemeralcontainer", "relation": "calls", "confidence": "INFERRED", "source_file": ".graphify_scope/pkg/kt/command/exchange/ephemeral.go", "source_location": "L28", "weight": 0.8}, {"source": "ephemeral_byephemeralcontainer", "target": "ephemeral_exchangewithephemeralcontainer", "relation": "calls", "confidence": "INFERRED", "source_file": ".graphify_scope/pkg/kt/command/exchange/ephemeral.go", "source_location": "L40", "weight": 0.8}, {"source": "ephemeral_getpodsofresource", "target": "ephemeral_getpodsofservice", "relation": "calls", "confidence": "INFERRED", "source_file": ".graphify_scope/pkg/kt/command/exchange/ephemeral.go", "source_location": "L66", "weight": 0.8}, {"source": "ephemeral_createephemeralcontainer", "target": "ephemeral_isephemeralcontainerready", "relation": "calls", "confidence": "INFERRED", "source_file": ".graphify_scope/pkg/kt/command/exchange/ephemeral.go", "source_location": "L94", "weight": 0.8}, {"source": "ephemeral_exchangewithephemeralcontainer", "target": "ephemeral_getlistenedports", "relation": "calls", "confidence": "INFERRED", "source_file": ".graphify_scope/pkg/kt/command/exchange/ephemeral.go", "source_location": "L126", "weight": 0.8}, {"source": "ephemeral_exchangewithephemeralcontainer", "target": "ephemeral_remoteredirectport", "relation": "calls", "confidence": "INFERRED", "source_file": ".graphify_scope/pkg/kt/command/exchange/ephemeral.go", "source_location": "L131", "weight": 0.8}, {"source": "ephemeral_exchangewithephemeralcontainer", "target": "ephemeral_setupiptables", "relation": "calls", "confidence": "INFERRED", "source_file": ".graphify_scope/pkg/kt/command/exchange/ephemeral.go", "source_location": "L140", "weight": 0.8}, {"source": "ephemeral_remoteredirectport", "target": "ephemeral_randport", "relation": "calls", "confidence": "INFERRED", "source_file": ".graphify_scope/pkg/kt/command/exchange/ephemeral.go", "source_location": "L205", "weight": 0.8}]}